chapeau.py
setup.py
Chapeau.egg-info/PKG-INFO
Chapeau.egg-info/SOURCES.txt
Chapeau.egg-info/dependency_links.txt
Chapeau.egg-info/top_level.txt