Metadata-Version: 1.0
Name: Chapeau
Version: 0.0.2
Summary: A very lightweight web framework
Home-page: https://github.com/lmontopo/Chapeau
Author: Leta Montopoli and Margo Smith
Author-email: lmontopo@gmail.com
License: UNKNOWN
Platform: UNKNOWN
